bundles/__init__.py
bundles/effect_bundles.py
effects/__init__.py
effects/image_effects.py
post_effects/__init__.py
post_effects/post_image_effects.py
scripts/pixel_sorting.py
taipan_imgfx-1.0.0.dist-info/licenses/LICENSE.md
utils/__init__.py
utils/fileman.py
utils/image.py
taipan_imgfx-1.0.0.dist-info/METADATA
taipan_imgfx-1.0.0.dist-info/WHEEL
taipan_imgfx-1.0.0.dist-info/top_level.txt
taipan_imgfx-1.0.0.dist-info/RECORD
