Metadata-Version: 2.4
Name: taipan_imgfx
Version: 1.0.0
Summary: A creative image manipulation toolkit.
Author-email: Bohdi Jakubik <bohdi.jakubik67@gmail.com>
License: Modified MIT-style license (Non-commercial)
Requires-Python: >=3.8
License-File: LICENSE.md
Dynamic: license-file
